certainty_estimator/__init__.py
certainty_estimator/edited_bert.py
certainty_estimator/predict_certainty.py
certainty_estimator-1.6.dist-info/LICENSE
certainty_estimator-1.6.dist-info/METADATA
certainty_estimator-1.6.dist-info/WHEEL
certainty_estimator-1.6.dist-info/top_level.txt
certainty_estimator-1.6.dist-info/RECORD
