Metadata-Version: 2.1
Name: certainty-estimator
Version: 1.6
Summary: This package is used to estimate certainty for scientific findings
Home-page: https://github.com/Jiaxin-Pei/certainty-estimator
Author: Jiaxin Pei
Author-email: pedropei@umich.edu
License: UNKNOWN
Platform: UNKNOWN
Requires-Python: >=3.6
License-File: LICENSE
